<?xml version="1.0"?>
<metadata xml:lang="en"><Esri><CreaDate>20221020</CreaDate><CreaTime>14534300</CreaTime><ArcGISFormat>1.0</ArcGISFormat><SyncOnce>TRUE</SyncOnce><ModDate>20240523</ModDate><ModTime>15234400</ModTime><scaleRange><minScale>150000000</minScale><maxScale>5000</maxScale></scaleRange><ArcGISProfile>ItemDescription</ArcGISProfile></Esri><tool name="DelineateWatershed" displayname="Step 2 - Delineate Watershed" toolboxalias="AgwaPythonToolboxAlias" xmlns=""><arcToolboxHelpPath>c:\program files\arcgis\pro\Resources\Help\gp</arcToolboxHelpPath><parameters><param name="Delineation_Workspace" displayname="Delineation Workspace" type="Required" direction="Input" datatype="Workspace" expression="Delineation_Workspace"/><param name="Outlet_Selection" displayname="Outlet Selection" type="Required" direction="Input" datatype="Feature Set" expression="Outlet_Selection"/><param name="Snap_Radius_(m)" displayname="Snap Radius (m)" type="Required" direction="Input" datatype="Double" expression="Snap_Radius_(m)"/><param name="Delineation_Name" displayname="Delineation Name" type="Required" direction="Input" datatype="String" expression="Delineation_Name"/><param name="Environment" displayname="Environment" type="Required" direction="Input" datatype="String" expression="ArcGIS Pro | ArcMap | Geoprocessing Service"/><param name="Debug" displayname="Debug messages" type="Optional" direction="Input" datatype="String" expression="{Debug}"/><param name="Save_Intermediate_Outputs" displayname="Save Intermediate Outputs" type="Optional" direction="Input" datatype="Boolean" expression="{Save_Intermediate_Outputs}"/></parameters></tool><dataIdInfo><idCitation><resTitle>Step 2 - Delineate Watershed</resTitle></idCitation></dataIdInfo><distInfo><distributor><distorFormat><formatName>ArcToolbox Tool</formatName></distorFormat></distributor></distInfo><mdHrLv><ScopeCd value="005"/></mdHrLv><mdDateSt Sync="TRUE">20240523</mdDateSt></metadata>
